dms_influx/__init__.py
dms_influx/data.py
dms_influx/decorators.py
dms_influx/functions.py
dms_influx/query.py
dms_influx-0.0.2.dist-info/METADATA
dms_influx-0.0.2.dist-info/WHEEL
dms_influx-0.0.2.dist-info/top_level.txt
dms_influx-0.0.2.dist-info/RECORD
