Metadata-Version: 2.1
Name: dms-influx
Version: 0.0.2
Summary: Library to connect and retrieve data from DMS oriented influxdb
Home-page: https://github.com/belingarb/dms-influx
Author: Bozidar Belingar
Author-email: bozidar.belingar@gmail.com
License: MIT
Platform: UNKNOWN
Classifier: License :: OSI Approved :: BSD License
Classifier: Programming Language :: Python :: 3.7
Classifier: Programming Language :: Python :: Implementation :: PyPy
Requires-Python: >=3.7.0
Requires-Dist: influxdb (~=5.3.1)
Requires-Dist: ciso8601 (~=2.1.3)
Requires-Dist: numpy (~=1.20.1)
Requires-Dist: urllib3 (~=1.26.3)
